Metadata-Version: 1.2
Name: sv2
Version: 1.5
Summary: SV2: Support Vector Structural Variation Genotyper
Home-page: https://github.com/dantaki/SV2
Author: Danny Antaki
Author-email: dantaki@ucsd.edu
License: MIT
Platform: UNKNOWN
Requires: cython
Requires: json
Requires: numpy
Requires: pandas
Requires: pybedtools
Requires: pysam
Requires: shutil
Requires: wget
Requires-Python: ~=2.7
